huaweicloudsdkdns/__init__.py
huaweicloudsdkdns/v2/__init__.py
huaweicloudsdkdns/v2/dns_async_client.py
huaweicloudsdkdns/v2/dns_client.py
huaweicloudsdkdns/v2/model/__init__.py
huaweicloudsdkdns/v2/model/alias_target.py
huaweicloudsdkdns/v2/model/associate_endpoint_ipaddress_request.py
huaweicloudsdkdns/v2/model/associate_endpoint_ipaddress_response.py
huaweicloudsdkdns/v2/model/associate_or_disassociate_router_with_rule_request_body.py
huaweicloudsdkdns/v2/model/associate_resolver_query_log_config_request.py
huaweicloudsdkdns/v2/model/associate_resolver_query_log_config_request_body.py
huaweicloudsdkdns/v2/model/associate_resolver_query_log_config_response.py
huaweicloudsdkdns/v2/model/associate_resolver_rule_router_request.py
huaweicloudsdkdns/v2/model/associate_resolver_rule_router_response.py
huaweicloudsdkdns/v2/model/associate_router_request.py
huaweicloudsdkdns/v2/model/associate_router_request_body.py
huaweicloudsdkdns/v2/model/associate_router_response.py
huaweicloudsdkdns/v2/model/batch_create_combined_public_recordsets_task_request.py
huaweicloudsdkdns/v2/model/batch_create_combined_public_recordsets_task_request_body.py
huaweicloudsdkdns/v2/model/batch_create_combined_public_recordsets_task_response.py
huaweicloudsdkdns/v2/model/batch_create_public_recordsets_task_item.py
huaweicloudsdkdns/v2/model/batch_create_public_recordsets_task_request.py
huaweicloudsdkdns/v2/model/batch_create_public_recordsets_task_request_body.py
huaweicloudsdkdns/v2/model/batch_create_public_recordsets_task_response.py
huaweicloudsdkdns/v2/model/batch_create_public_zones_task_request.py
huaweicloudsdkdns/v2/model/batch_create_public_zones_task_request_body.py
huaweicloudsdkdns/v2/model/batch_create_public_zones_task_response.py
huaweicloudsdkdns/v2/model/batch_create_record_set_with_line.py
huaweicloudsdkdns/v2/model/batch_create_record_sets_task_item.py
huaweicloudsdkdns/v2/model/batch_create_record_sets_task_request.py
huaweicloudsdkdns-3.1.184.dist-info/METADATA
huaweicloudsdkdns-3.1.184.dist-info/WHEEL
huaweicloudsdkdns-3.1.184.dist-info/licenses/LICENSE
huaweicloudsdkdns-3.1.184.dist-info/RECORD
